{
    "personal_info": {
        "first_name": "Oscar",
        "last_name": "Borrezo",
        "email": "obpalomo@gmail.com",
        "phone": "+34 675 892 443",
        "location": {
            "country": "España",
            "city": "Barcelona",
            "state": "España"
        },
        "linkedin": "www.linkedin.com/in/óscar-b-ab6b27192",
        "website": "",
        "portfolio": "",
        "summary": "Experienced software engineer with expertise in web development and cloud computing."
    },
    "work_experience": [],
    "education": [
        {
            "degree": "Bootcamp Full Stack Developer",
            "institution": "Upgrade Hub",
            "location": "Madrid, ES",
            "start_date": "2023-09-01",
            "end_date": "2024-05-01",
            "hours": 350
        },
        {
            "degree": "Diplomatura Ciencias Empresariales",
            "institution": "Univeridad Malaga",
            "location": "Malaga, ES",
            "start_date": "2006-09-01",
            "end_date": "2010-07-01"
        }
    ],
    "skills": {
        "keywords": {
            "technical": [
                "javaScript",
                "react",
                "angular",
                "node.js",
                "html",
                "css",
                "noSql",
                "sql",
                "php"
            ],
            "soft": [
                "leadership",
                "communication",
                "problem-solving"
            ],
            "tools": [
                "figma",
                "trello"
            ]
        },
        "detailed": {
            "technical": {
                "javaScript": [
                    {
                        "id": 1001,
                        "title": "Variables and Data Types",
                        "description": "Declaración de variables usando var, let y const, y comprensión de tipos primitivos y objetos.",
                        "repository_url": "https://github.com/obpalomo/Estructura-js/blob/master/Exercises/1001.js"
                    },
                    {
                        "id": 1002,
                        "title": "Control Flow",
                        "description": "Uso de instrucciones condicionales y bucles (if, else, switch, for, while).",
                        "repository_url": "https://github.com/obpalomo/Estructura-js/blob/master/Exercises/1002.js"
                    }
                ]
            }
        }
    },
    "certifications": [],
    "projects": [
        {
            "name": "Maravillas de España",
            "description": "Proyecto Final Bootcamp",
            "technologies": ["JS", "react","MongoDB", "node"],
            "url": "https://maravillas-de-espana-frontend.vercel.app/"
        }
    ],
    "languages": [
        {
            "language": "Español",
            "proficiency": "Native"
        },
        {
            "language": "English",
            "proficiency": "Basico"
        }
    ],
    "volunteer_experience": [],
    "publications": [],
    "references": []
}