{
    "personal_info": {
        "first_name": "Karen Edith",
        "last_name": "Moreno",
        "email": "karedimor@gmail.com",
        "phone": "+57 3012609225",
        "location": {
            "country": "",
            "city": "",
            "state": ""
        },
        "linkedin": "https://www.linkedin.com/in/karen-moreno-a99992a7/",
        "website": "",
        "portfolio": "https://github.com/KarenAmor",
        "summary": "Backend engineer with over two years of experience. Creative and autonomous professional, passionate about entrepreneurship and building reliable systems that scale quickly. Experienced in projects involving role management, handling sensitive data, and task automation."
    },
    "work_experience": [
        {
            "job_title": "Backend Engineer",
            "company": "Credicorp Capital",
            "location": "",
            "start_date": "2022-02-01",
            "end_date": "2024-07-31",
            "currently_working": false,
            "responsibilities": [
                "Created CRUDs and developed digital solutions for role, segment, and notification management.",
                "Enhanced customer experience and facilitated continuous growth through technical solutions."
            ],
            "achievements": [
                "Highlighted in a video for Women in STEAM Day as part of recognition for contributions."
            ],
            "repository_url": ""
        }
    ],
    "education": [
        {
            "degree": "Azure Developer Associate",
            "institution": "Código Facilito",
            "location": "",
            "start_date": "",
            "end_date": "",
            "hours": 0
        },
        {
            "degree": "Coastal Zone Ecology",
            "institution": "University of Antioquia",
            "location": "",
            "start_date": "",
            "end_date": "",
            "hours": 0
        },
        {
            "degree": "Data Science Diploma in Python",
            "institution": "University EAFIT",
            "location": "",
            "start_date": "",
            "end_date": "",
            "hours": 0
        },
        {
            "degree": "Full Stack Web Development Bootcamp",
            "institution": "Digital House",
            "location": "",
            "start_date": "",
            "end_date": "",
            "hours": 0
        }
    ],
    "skills": {
        "keywords": {
            "technical": [
                "javascript",
                "typescript",
                "express.js",
                "nest.js",
                "sql",
                "supabase",
                "python",
                "fastapi",
                "unit-testing",
                "azure",
                "docker",
                "git"
            ],
            "soft": [],
            "tools": []
        },
        "detailed": {
            "technical": {},
            "soft": {}
        }
    },
    "certifications": [],
    "projects": [
        {
            "name": "Backoffice Portal",
            "description": "Developed a backoffice portal for user management at Credicorp Capital, enhancing administrative efficiency and user experience.",
            "technologies": [],
            "url": ""
        },
        {
            "name": "Tagging System",
            "description": "Created a tagging system for tailored user experiences, improving customer satisfaction and engagement.",
            "technologies": [],
            "url": ""
        },
        {
            "name": "Client Registration System",
            "description": "Implemented a client registration system that streamlined communication and service delivery to bankers and advisors.",
            "technologies": [],
            "url": ""
        }
    ],
    "languages": [],
    "volunteer_experience": [],
    "publications": [],
    "references": [
        {
            "name": "Gustavo Enrique Barragan",
            "relationship": "",
            "contact": "https://www.linkedin.com/in/gustavo-barragan480933194/ +57 (314) 3390071"
        },
        {
            "name": "Andrea Marcela Mejia",
            "relationship": "",
            "contact": "https://www.linkedin.com/in/andrea-marcela-mejia-ortega-2734248a/ +1 (318) 8957823"
        }
    ]
}