{
    "personal_info": {
        "first_name": "Nelson Mariano",
        "last_name": "Rojas Bustos",
        "email": "nelmrb@gmail.com",
        "phone": "543512175299",
        "location": {
            "country": "",
            "city": "",
            "state": ""
        },
        "linkedin": "https://linkedin.com/in/nelson-mariano-rojas-bustos-127aa277",
        "website": "",
        "portfolio": "",
        "summary": "QA Manual and Systems Analyst with experience in customer service, emergency dispatch, and office administration. Proven ability to resolve problems, work under pressure, and manage teams in dynamic environments. Currently pursuing a Bachelor's degree in Data Science and enhancing skills in Full Stack development with Python. Seeking remote or in-person opportunities to apply QA and analytical skills, with a focus on data-driven solutions. Open to TRAINNER and entry-level positions."
    },
    "work_experience": [
        {
            "job_title": "Emergency Dispatcher",
            "company": "Emergencias Medicas Integral",
            "location": "",
            "start_date": "2014-05-01",
            "end_date": "",
            "currently_working": true,
            "responsibilities": [
                "Managed emergency situations and coordinated national patient transfers, resulting in a 15% improvement in response times.",
                "Implemented a new system for tracking patient transfers, increasing efficiency by 20%.",
                "Trained new dispatchers on emergency protocols and QA procedures, achieving 100% compliance.",
                "Conducted quality assurance checks on dispatch logs, ensuring accuracy and compliance with regulations.",
                "Provided excellent customer service to individuals in distress, maintaining composure under pressure.",
                "Coordinated PAMI patient transfers, streamlining the process and reducing wait times by 10%."
            ],
            "achievements": [],
            "repository_url": ""
        },
        {
            "job_title": "Customer Service Agent/Supervisor",
            "company": "Xerox",
            "location": "",
            "start_date": "2007-12-01",
            "end_date": "2011-07-01",
            "currently_working": false,
            "responsibilities": [
                "Provided customer support for Claro 611, resolving an average of 50 customer issues per day.",
                "Supervised a team of 5 customer service representatives during peak periods, ensuring service quality.",
                "Trained new hires on customer service procedures and QA protocols, improving first call resolution by 10%.",
                "Conducted regular QA checks on call recordings, identifying areas for improvement and providing feedback to team members.",
                "Implemented a new system for tracking customer complaints, reducing resolution times by 15%.",
                "Successfully handled escalated customer issues, achieving a 90% customer satisfaction rating."
            ],
            "achievements": [],
            "repository_url": ""
        },
        {
            "job_title": "Office Manager",
            "company": "Estudio Dra Caruzzo",
            "location": "",
            "start_date": "2007-11-01",
            "end_date": "2010-03-01",
            "currently_working": false,
            "responsibilities": [
                "Managed all office administrative tasks, including data entry, filing, and scheduling, increasing office efficiency by 20%.",
                "Migrated paper-based database to a digital system, improving data accuracy by 15% and reducing retrieval time by 50%.",
                "Managed and maintained office IT equipment, ensuring smooth operation and minimal downtime.",
                "Implemented new filing system for client records, improving organization and retrieval time by 25%.",
                "Trained staff on new software and database usage, ensuring successful adoption and improved productivity.",
                "Developed and implemented new office procedures, streamlining operations and reducing administrative costs by 10%."
            ],
            "achievements": [],
            "repository_url": ""
        }
    ],
    "education": [
        {
            "degree": "Bachelor of Science in Data Science (In Progress)",
            "institution": "Instituto Santo Domingo",
            "location": "Cordoba",
            "start_date": "",
            "end_date": ""
        },
        {
            "degree": "Tecnico Superior en Analisis de Sistemas",
            "institution": "Instituto Superior Santo Domingo",
            "location": "Cordoba",
            "start_date": "2013-03-01",
            "end_date": "2017-09-01",
            "hours": 0
        },
        {
            "degree": "Bachiller En Economia y Gestion de las Organizaciones",
            "institution": "Instituto Jose Manuel Estrada",
            "location": "Villa de Soto, Cba",
            "start_date": "1999-03-01",
            "end_date": "2004-12-01",
            "hours": 0
        }
    ],
    "skills": {
        "keywords": {
            "technical": [
                "sql",
                "python",
                "data-analysis",
                "qa-manual",
                "qa-automation",
                "software-testing",
                "database-management"
            ],
            "soft": [
                "customer-service",
                "communication",
                "teamwork",
                "problem-solving",
                "adaptability",
                "time-management",
                "decision-making",
                "leadership",
                "training",
                "work-under-pressure",
                "learning-agility",
                "remote-work"
            ],
            "tools": []
        },
        "detailed": {
            "technical": {},
            "soft": {}
        }
    },
    "certifications": [
        {
            "name": "QA Automation",
            "issuing_organization": "XAcademy",
            "issue_date": "",
            "expiration_date": "",
            "credential_id": ""
        },
        {
            "name": "QA Manual",
            "issuing_organization": "XAcademy",
            "issue_date": "",
            "expiration_date": "",
            "credential_id": ""
        },
        {
            "name": "TESTING + Q.A.",
            "issuing_organization": "Instituto Taborin",
            "issue_date": "",
            "expiration_date": "",
            "credential_id": ""
        },
        {
            "name": "Google AI Essentials",
            "issuing_organization": "Coursera",
            "issue_date": "",
            "expiration_date": "",
            "credential_id": ""
        },
        {
            "name": "Agile Explorer",
            "issuing_organization": "IBM SkillsBuild",
            "issue_date": "",
            "expiration_date": "",
            "credential_id": ""
        },
        {
            "name": "Bases de Datos SQL",
            "issuing_organization": "ICARO",
            "issue_date": "",
            "expiration_date": "",
            "credential_id": ""
        }
    ],
    "projects": [],
    "languages": [],
    "volunteer_experience": [],
    "publications": [],
    "references": []
}