{
    "personal_info": {
        "first_name": "Candelaria",
        "last_name": "Chalub",
        "email": "candelariachalub@gmail.com",
        "phone": "+54 9 351 521 3902",
        "location": {
            "country": "Argentina",
            "city": "Buenos Aires",
            "state": ""
        },
        "linkedin": "https://www.linkedin.com/in/candelariachalub/",
        "website": "",
        "portfolio": "",
        "summary": "Full Stack Developer con experiencia en backend con Java y frontend con Angular y React. Apasionada por la tecnología, la optimización de procesos y el aprendizaje continuo."
    },
    "work_experience": [
        {
            "job_title": "Full Stack Developer",
            "company": "Quinto Impacto IT Consultancy",
            "location": "",
            "start_date": "2023-02-01",
            "end_date": "",
            "currently_working": true,
            "responsibilities": [
                "Desarrollo de soluciones back-end en Java",
                "Diseño y desarrollo de herramientas escalables",
                "Participación en proyectos clave como Papelería ER y COEF"
            ],
            "achievements": [],
            "repository_url": ""
        },
        {
            "job_title": "Developer PHP & React.js",
            "company": "Proyecto Part-Time para cliente",
            "location": "",
            "start_date": "2024-09-01",
            "end_date": "",
            "currently_working": true,
            "responsibilities": [
                "Desarrollo de una página web de e-commerce",
                "Creación de una experiencia de usuario intuitiva",
                "Implementación de soluciones personalizadas"
            ],
            "achievements": [],
            "repository_url": ""
        }
    ],
    "education": [
        {
            "degree": "Full Stack Java Developer",
            "institution": "MindHub LA",
            "location": "",
            "start_date": "",
            "end_date": "",
            "hours": 0
        },
        {
            "degree": "Systems Engineering (Student)",
            "institution": "UDEMM",
            "location": "",
            "start_date": "",
            "end_date": "",
            "hours": 0
        }
    ],
    "skills": {
        "keywords": {
            "technical": [
                "java", "angular", "typescript", "node.js", "css", "html", "javascript", "sass", "axios", "bootstrap", "spring-boot", "postgresql", "vue.js", "php", "react.js"
            ],
            "soft": [
                "teamwork", "communication", "problem-solving", "leadership", "time-management"
            ],
            "tools": [
                "jira", "trello"]
        },
        "detailed": {}
    },
    "certifications": [],
    "projects": [],
    "languages": [
        {
            "language": "Español",
            "proficiency": "Nativo"
        },
        {
            "language": "Inglés",
            "proficiency": "Intermedio"
        },
        {
            "language": "Portugués",
            "proficiency": "Avanzado"
        }
    ],
    "volunteer_experience": [],
    "publications": [],
    "references": []
}
