{
    "personal_info": {
        "first_name": "Gaston Emilio",
        "last_name": "Carrizo",
        "email": "gastoncarrizo123@gmail.com",
        "phone": "+5493815542748",
        "location": {
            "country": "Argentina",
            "city": "Yerba Buena",
            "state": "Tucumán"
        },
        "linkedin": "",
        "website": "",
        "portfolio": "",
        "summary": "Desarrollador en busca de experiencia en proyectos de software y desarrollo web. Comprometido con el aprendizaje continuo y la mejora de mis habilidades técnicas para contribuir a soluciones innovadoras."
    },
    "work_experience": [
        {
            "job_title": "Empleado",
            "company": "JC Drugstore",
            "location": "",
            "start_date": "2021-12-01",
            "end_date": "2023-04-30",
            "currently_working": false,
            "responsibilities": [
                "Atención al cliente",
                "Reposición de mercadería",
                "Control de stock"
            ],
            "achievements": [],
            "repository_url": ""
        }
    ],
    "education": [
        {
            "degree": "Tecnicatura Universitaria en Programación",
            "institution": "Universidad Tecnologica Nacional | UTN - FRT",
            "location": "",
            "start_date": "2022-03-01",
            "end_date": "2024-09-01",
            "hours": 0
        }
    ],
    "skills": {
        "keywords": {
            "technical": [
                "python",
                "javascript",
                "react-js",
                "git"
            ],
            "soft": [],
            "tools": []
        },
        "detailed": {
            "technical": {},
            "soft": {}
        }
    },
    "certifications": [],
    "projects": [],
    "languages": [
        {
            "language": "Castellano",
            "proficiency": "Nativo"
        },
        {
            "language": "Inglés",
            "proficiency": "Básico"
        }
    ],
    "volunteer_experience": [],
    "publications": [],
    "references": []
}