{
    "personal_info": {
        "first_name": "Francisco",
        "last_name": "Blanarik",
        "email": "frantigre2000@gmail.com",
        "phone": "+54 911 59197156",
        "location": {
            "country": "Argentina",
            "city": "San Fernando",
            "state": "Buenos Aires"
        },
        "linkedin": "",
        "website": "",
        "portfolio": "",
        "summary": "Soy una persona adaptable con habilidades tanto para el trabajo en equipo como para el trabajo individual. Valoro el respeto, la puntualidad y la organización, y los considero esenciales en cualquier trabajo. Mi objetivo es desarrollarme en un lugar donde pueda aportar y seguir aprendiendo, siempre fomentando un ambiente agradable y de colaboración."
    },
    "work_experience": [
        {
            "job_title": "Asistente de contador",
            "company": "",
            "location": "",
            "start_date": "2022-06-01",
            "end_date": "2023-12-31",
            "currently_working": false,
            "responsibilities": [
                "Colaboración en tareas contables y administrativas, como conciliaciones bancarias y manejo de documentación."
            ],
            "achievements": [],
            "repository_url": ""
        },
        {
            "job_title": "Auxiliar contable jr.",
            "company": "Sleep & Co.",
            "location": "",
            "start_date": "2023-06-01",
            "end_date": "2023-12-31",
            "currently_working": false,
            "responsibilities": [
                "Uso del Sistema Colppy, para la gestión contable y administrativa."
            ],
            "achievements": [],
            "repository_url": ""
        }
    ],
    "education": [
        {
            "degree": "Tecnicatura Universitaria en Programación",
            "institution": "UTN-FRGP",
            "location": "",
            "start_date": "",
            "end_date": "",
            "hours": 0
        },
        {
            "degree": "Bachiller con orientación en Ciencias Sociales",
            "institution": "EES N°10. BATALLA de LA VUELTA OBLIGADO",
            "location": "",
            "start_date": "",
            "end_date": "2021-12-31",
            "hours": 0
        }
    ],
    "skills": {
        "keywords": {
            "technical": [
                "microsoft-office",
                "c++",
                "html",
                "css"
            ],
            "soft": [
                "proactividad",
                "adaptabilidad",
                "colaboración",
                "responsabilidad",
                "comunicación"
            ],
            "tools": []
        },
        "detailed": {
            "technical": {},
            "soft": {}
        }
    },
    "certifications": [],
    "projects": [],
    "languages": [
        {
            "language": "Spanish",
            "proficiency": "Native"
        },
        {
            "language": "English",
            "proficiency": "Basic"
        }
    ],
    "volunteer_experience": [],
    "publications": [],
    "references": []
}