{
    "personal_info": {
        "first_name": "Jhon Renzo",
        "last_name": "Huacho Janampa",
        "email": "jhonhuacho537@gmail.com",
        "phone": "918805854",
        "location": {
            "country": "Peru",
            "city": "Pichanaki",
            "state": ""
        },
        "linkedin": "",
        "website": "",
        "portfolio": "",
        "summary": "Especialista en informática altamente responsable, creativo, con iniciativa y puntualidad, adaptado a las condiciones laborales, con gusto por trabajar en equipo, resolver problemas de manera eficaz y lograr las metas de la organización."
    },
    "work_experience": [
        {
            "job_title": "Coordinador de Innovación Soporte Tecnológico",
            "company": "Ugel Pichanaki",
            "location": "Pichanaki",
            "start_date": "2024-05-01",
            "end_date": "2024-12-31",
            "currently_working": false,
            "responsibilities": [
                "Gestionar el control presupuestario, los cierres mensuales y anuales.",
                "Formar y capacitar a los docentes en el uso de nuevas herramientas y tecnologías."
            ],
            "achievements": [],
            "repository_url": ""
        },
        {
            "job_title": "Coordinador de Innovación Soporte Tecnológico",
            "company": "Ugel Pichanaki",
            "location": "Pichanaki",
            "start_date": "2022-09-01",
            "end_date": "2022-12-31",
            "currently_working": false,
            "responsibilities": [
                "Planificar la gestión de las actividades correspondientes al uso de recursos tecnológicos.",
                "Velar por la seguridad de las aulas funcionales TIC y de los recursos tecnológicos."
            ],
            "achievements": [],
            "repository_url": ""
        },
        {
            "job_title": "Coordinador de Innovación Soporte Tecnológico",
            "company": "Ugel Pichanaki",
            "location": "Pichanaki",
            "start_date": "2022-03-01",
            "end_date": "2022-06-30",
            "currently_working": false,
            "responsibilities": [
                "Supervisar las instalaciones y mantenimiento de los equipos informáticos y de comunicación.",
                "Desarrollar y ejecutar propuestas de formación en alfabetización digital al personal."
            ],
            "achievements": [],
            "repository_url": ""
        },
        {
            "job_title": "Practicas Profesional",
            "company": "Ugel Pichanaki",
            "location": "Pichanaki",
            "start_date": "2018-09-01",
            "end_date": "2018-12-31",
            "currently_working": false,
            "responsibilities": [
                "Mantenimiento de Equipos",
                "Gestión y Actualización de Bases de Datos",
                "Desarrollo de Contenidos Digitales"
            ],
            "achievements": [],
            "repository_url": ""
        },
        {
            "job_title": "Soporte Técnico",
            "company": "Instituto Cebanfi",
            "location": "",
            "start_date": "2017-01-01",
            "end_date": "2017-12-31",
            "currently_working": false,
            "responsibilities": [
                "Gestión de Redes y Conectividad",
                "Asistencia a Usuarios y Capacitación"
            ],
            "achievements": [],
            "repository_url": ""
        },
        {
            "job_title": "Asistente Administrativo",
            "company": "Inversiones Inseju",
            "location": "",
            "start_date": "2016-01-01",
            "end_date": "2016-12-31",
            "currently_working": false,
            "responsibilities": [
                "Gestión de Documentación y Archivos"
            ],
            "achievements": [],
            "repository_url": ""
        }
    ],
    "education": [
        {
            "degree": "Técnico en Computación e Informática",
            "institution": "Servicio Nacional de Adiestramiento en Trabajo Industrial",
            "location": "Pichanaki",
            "start_date": "2020-02-01",
            "end_date": "",
            "hours": 0
        },
        {
            "degree": "Bachiller Ingeniería de Sistemas e Informática",
            "institution": "Universidad Continental",
            "location": "",
            "start_date": "",
            "end_date": "2024-03-01",
            "hours": 0
        }
    ],
    "skills": {
        "keywords": {
            "technical": ["paquete-office", "inglés"],
            "soft": ["orientación-al-cliente", "liderazgo"],
            "tools": []
        },
        "detailed": {
            "technical": {},
            "soft": {}
        }
    },
    "certifications": [
        {
            "name": "SIAF-RP Y SIGA-MEF 100% PRACTICO",
            "issuing_organization": "INSTITUTO DE ESPECIALIZACIÓN Y CAPACITACIÓN LA CATÓLICA",
            "issue_date": "",
            "expiration_date": "",
            "credential_id": ""
        },
        {
            "name": "SISTEMA NACIONAL DE PROGRAMACIÓN MULTI ANUAL Y GESTIONES DE INVERSIONES - INVIERTE.PE",
            "issuing_organization": "INSTITUTO DE ESPECIALIZACIÓN Y CAPACITACIÓN LA CATÓLICA",
            "issue_date": "",
            "expiration_date": "",
            "credential_id": ""
        },
        {
            "name": "ASISTENTE ADMINISTRATIVO",
            "issuing_organization": "INSTITUTO DE ESPECIALIZACIÓN Y CAPACITACIÓN LA CATÓLICA",
            "issue_date": "",
            "expiration_date": "",
            "credential_id": ""
        },
        {
            "name": "FUNDAMENTOS DE LA ATENCIÓN AL CLIENTE PARA PROFESIONALES IT",
            "issuing_organization": "LINKEDIN LEARNING",
            "issue_date": "",
            "expiration_date": "",
            "credential_id": ""
        },
        {
            "name": "TABLAS DINÁMICAS MICROSOFT EXCEL",
            "issuing_organization": "CÁMARA DE COMERCIO Y CAPACITACIÓN INTERNACIONAL",
            "issue_date": "",
            "expiration_date": "",
            "credential_id": ""
        },
        {
            "name": "PRINCIPIANTE EN PROGRAMACIÓN G6",
            "issuing_organization": "ONE - ORACLE +ALURA LATAM",
            "issue_date": "",
            "expiration_date": "",
            "credential_id": ""
        },
        {
            "name": "INTELIGENCIA ARTIFICIAL CON BUSINESS INTELLIGENCE EN EXCEL",
            "issuing_organization": "UNI",
            "issue_date": "",
            "expiration_date": "",
            "credential_id": ""
        }
    ],
    "projects": [],
    "languages": [
        {
            "language": "English",
            "proficiency": "Basic"
        }
    ],
    "volunteer_experience": [],
    "publications": [],
    "references": []
}